odd_or_even/__init__.py
odd_or_even/check.py
odd_or_even_meenadevi-0.0.1.dist-info/licenses/LICENSE
odd_or_even_meenadevi-0.0.1.dist-info/METADATA
odd_or_even_meenadevi-0.0.1.dist-info/WHEEL
odd_or_even_meenadevi-0.0.1.dist-info/top_level.txt
odd_or_even_meenadevi-0.0.1.dist-info/RECORD
