Metadata-Version: 2.4
Name: odd_or_even_meenadevi
Version: 0.0.1
Summary: A simple Python package to check whether a number is odd or even.
Author-email: Meenadevi <example@example.com>
License: MIT
Requires-Python: >=3.7
License-File: LICENSE
Dynamic: license-file
